promptcachedb_client/__init__.py
promptcachedb_client/cache_pipeline.py
promptcachedb_client/client.py
promptcachedb_client/prompt_metadata.py
promptcachedb_client-0.1.0.dist-info/METADATA
promptcachedb_client-0.1.0.dist-info/WHEEL
promptcachedb_client-0.1.0.dist-info/entry_points.txt
promptcachedb_client-0.1.0.dist-info/RECORD
