Metadata-Version: 2.3
Name: promptcachedb-client
Version: 0.1.0
Summary: promptcachedb client
Requires-Python: >=3.12
Requires-Dist: requests>=2.32.3
Requires-Dist: torch>=2.4.1
Requires-Dist: transformers>=4.45.2
